pyhmy/__init__.py
pyhmy/_version.py
pyhmy/account.py
pyhmy/blockchain.py
pyhmy/cli.py
pyhmy/contract.py
pyhmy/exceptions.py
pyhmy/logging.py
pyhmy/numbers.py
pyhmy/signing.py
pyhmy/staking.py
pyhmy/staking_signing.py
pyhmy/staking_structures.py
pyhmy/transaction.py
pyhmy/util.py
pyhmy/validator.py
pyhmy/rpc/__init__.py
pyhmy/rpc/exceptions.py
pyhmy/rpc/request.py
pyhmy-20.5.21.dist-info/LICENSE.txt
pyhmy-20.5.21.dist-info/METADATA
pyhmy-20.5.21.dist-info/WHEEL
pyhmy-20.5.21.dist-info/top_level.txt
pyhmy-20.5.21.dist-info/RECORD
