Metadata-Version: 2.1
Name: pyhmy
Version: 20.5.21
Summary: A library for interacting and working the Harmony blockchain and related codebases.
Home-page: http://harmony.one/
Author: Daniel Van Der Maden
Author-email: daniel@harmony.one
License: MIT
Keywords: Harmony,blockchain,protocol
Platform: UNKNOWN
Requires-Dist: pexpect
Requires-Dist: requests
Requires-Dist: incremental
Requires-Dist: eth-rlp
Requires-Dist: eth-account (==0.5.4)
Requires-Dist: eth-utils
Requires-Dist: hexbytes
Requires-Dist: cytoolz
